{
  "id": "s8-run",
  "name": "s8-run",
  "title": "S8 Run 面板真实实现",
  "description": "真实 token/费用/工具统计/运行时长",
  "status": "completed",
  "dev_type": null,
  "scope": null,
  "package": null,
  "priority": "P1",
  "creator": "justhil",
  "assignee": "justhil",
  "createdAt": "2026-06-19",
  "completedAt": "2026-06-19",
  "branch": null,
  "base_branch": "master",
  "worktree_path": null,
  "commit": null,
  "pr_url": null,
  "subtasks": [],
  "children": [],
  "parent": "06-19-pi-desktop-product",
  "relatedFiles": [],
  "notes": "",
  "meta": {}
}